st_cockroachdb_connection/__init__.py
st_cockroachdb_connection/connection.py
st_cockroachdb_connection/util.py
st_cockroachdb_connection-1.0.1.dist-info/LICENSE
st_cockroachdb_connection-1.0.1.dist-info/METADATA
st_cockroachdb_connection-1.0.1.dist-info/WHEEL
st_cockroachdb_connection-1.0.1.dist-info/top_level.txt
st_cockroachdb_connection-1.0.1.dist-info/RECORD
