Metadata-Version: 2.1
Name: st-cockroachdb-connection
Version: 1.0.1
Summary: Streamlit Connection for CockroachDB.
Author-email: Putu Widyantara Artanta Wibawa <putuwaw973@gmail.com>
License: MIT License
Project-URL: Repository, https://github.com/putuwaw/st-cockroachdb-connection
Project-URL: Documentation, https://experimental-connection.streamlit.app/
Keywords: streamlit,cockroachdb,connection
Classifier: Programming Language :: Python :: 3
Classifier: License :: OSI Approved :: MIT License
Classifier: Operating System :: OS Independent
Requires-Python: >=3.8
License-File: LICENSE
Requires-Dist: streamlit>=1.28.0
Requires-Dist: psycopg[binary]
Provides-Extra: dev
Requires-Dist: pytest; extra == "dev"
Requires-Dist: st-pages; extra == "dev"
